MANIFEST.in
Makefile
README.txt
setup.py
timelib.c
timelib.pyx
timelib_config.h
ext-date-lib/README
ext-date-lib/astro.c
ext-date-lib/astro.h
ext-date-lib/dow.c
ext-date-lib/fallbackmap.h
ext-date-lib/parse_date.c
ext-date-lib/parse_date.re
ext-date-lib/parse_tz.c
ext-date-lib/timelib.c
ext-date-lib/timelib.h
ext-date-lib/timelib.m4
ext-date-lib/timelib_config.h.win32
ext-date-lib/timelib_structs.h
ext-date-lib/timezonedb.h
ext-date-lib/timezonemap.h
ext-date-lib/tm2unixtime.c
ext-date-lib/unixtime2tm.c
timelib.egg-info/PKG-INFO
timelib.egg-info/SOURCES.txt
timelib.egg-info/dependency_links.txt
timelib.egg-info/not-zip-safe
timelib.egg-info/top_level.txt