Metadata-Version: 1.0
Name: timelib
Version: 0.2.2
Summary: parse english textual date descriptions
Home-page: http://github.com/schmir/timelib/tree/master
Author: Ralf Schmitt
Author-email: schmir@gmail.com
License: zlib/php
Platform: UNKNOWN
